burdock_lab/__init__.py
burdock_lab-0.0.7a2.dist-info/METADATA
burdock_lab-0.0.7a2.dist-info/WHEEL
burdock_lab-0.0.7a2.dist-info/top_level.txt
burdock_lab-0.0.7a2.dist-info/RECORD
