Metadata-Version: 2.1
Name: burdock-lab
Version: 0.0.7a2
Summary: JupyterLab integration for Burdock, a Daikon frontend for data frames.
Home-page: https://github.com/DylanLukes/burdock_lab
Author: Dylan A. Lukes
Author-email: dlukes@eng.ucsd.edu
License: BSD 3-Clause
Platform: UNKNOWN
Requires-Dist: burdock
